s3aads/__init__.py
s3aads/copy.py
s3aads/database.py
s3aads/resources.py
s3aads/table.py
s3aads-2.13.6.dist-info/LICENSE
s3aads-2.13.6.dist-info/METADATA
s3aads-2.13.6.dist-info/WHEEL
s3aads-2.13.6.dist-info/top_level.txt
s3aads-2.13.6.dist-info/RECORD
