Metadata-Version: 2.1
Name: s3aads
Version: 2.13.6
Summary: S3-as-a-datastore is a library that lives on top of botocore and boto3, as a way to use S3 as a key-value datastore instead of a real datastore
Home-page: https://github.com/joeyism/s3-as-a-datastore
Author: joeyism
Author-email: joeyism@gmail.com
License: UNKNOWN
Download-URL: https://github.com/joeyism/s3-as-a-datastore/archive/2.13.6.tar.gz
Keywords: aws,s3,datastore
Platform: UNKNOWN
License-File: LICENSE
Requires-Dist: botocore
Requires-Dist: boto3
